odoo10_addon_l10n_it_fatturapa_in_purchase-10.0.1.0.0.99.dev15-py3.8-nspkg.pth
odoo/addons/l10n_it_fatturapa_in_purchase/README.rst
odoo/addons/l10n_it_fatturapa_in_purchase/__init__.py
odoo/addons/l10n_it_fatturapa_in_purchase/__manifest__.py
odoo/addons/l10n_it_fatturapa_in_purchase/i18n/it.po
odoo/addons/l10n_it_fatturapa_in_purchase/i18n/l10n_it_fatturapa_in_purchase.pot
odoo/addons/l10n_it_fatturapa_in_purchase/models/__init__.py
odoo/addons/l10n_it_fatturapa_in_purchase/models/purchase_order.py
odoo/addons/l10n_it_fatturapa_in_purchase/readme/CONTRIBUTORS.rst
odoo/addons/l10n_it_fatturapa_in_purchase/readme/DESCRIPTION.rst
odoo/addons/l10n_it_fatturapa_in_purchase/readme/USAGE.rst
odoo/addons/l10n_it_fatturapa_in_purchase/static/description/icon.png
odoo/addons/l10n_it_fatturapa_in_purchase/static/description/index.html
odoo/addons/l10n_it_fatturapa_in_purchase/views/invoice_view.xml
odoo10_addon_l10n_it_fatturapa_in_purchase-10.0.1.0.0.99.dev15.dist-info/METADATA
odoo10_addon_l10n_it_fatturapa_in_purchase-10.0.1.0.0.99.dev15.dist-info/WHEEL
odoo10_addon_l10n_it_fatturapa_in_purchase-10.0.1.0.0.99.dev15.dist-info/namespace_packages.txt
odoo10_addon_l10n_it_fatturapa_in_purchase-10.0.1.0.0.99.dev15.dist-info/top_level.txt
odoo10_addon_l10n_it_fatturapa_in_purchase-10.0.1.0.0.99.dev15.dist-info/RECORD
