Metadata-Version: 2.1
Name: odoo10-addon-l10n-it-fatturapa-in-purchase
Version: 10.0.1.0.0.99.dev15
Summary: Modulo ponte tra ricezione fatture elettroniche e acquisti
Home-page: https://github.com/OCA/l10n-italy/tree/10.0/l10n_it_fatturapa_in_purchase
Author: Agile Business Group, Odoo Community Association (OCA)
Author-email: support@odoo-community.org
License: LGPL-3
Platform: UNKNOWN
Classifier: Programming Language :: Python
Classifier: Framework :: Odoo
Classifier: Framework :: Odoo :: 10.0
Classifier: License :: OSI Approved :: GNU Lesser General Public License v3 (LGPLv3)
Requires-Python: ~=2.7
Requires-Dist: odoo10-addon-l10n-it-fatturapa-in
Requires-Dist: odoo <10.1dev,>=10.0
